noobai/__init__.py
noobai/data/__init__.py
noobai/data/util.py
noobai/datasets/__init__.py
noobai/datasets/cv/__init__.py
noobai/datasets/cv/classify.py
noobai/datasets/nlp/__init__.py
noobai/datasets/nlp/book.py
noobai/datasets/nlp/qa.py
noobai/datasets/nlp/translate.py
noobai/model/__init__.py
noobai/model/sam/__init__.py
noobai/model/sam/main.py
noobai/model/sam/model.py
noobai/model/sam/configs/number_recall.json
noobai/module/__init__.py
noobai/module/nn/loss.py
noobai/module/nn/lr_scheduler.py
noobai/module/nn/resblock.py
noobai/task/__init__.py
noobai/task/eval/__init__.py
noobai/task/eval/nlp/__init__.py
noobai/task/memory/__init__.py
noobai/task/memory/number_recall.py
noobai/util/init.py
noobai/util/trainer.py
noobai-0.0.2.dist-info/LICENSE
noobai-0.0.2.dist-info/METADATA
noobai-0.0.2.dist-info/WHEEL
noobai-0.0.2.dist-info/top_level.txt
noobai-0.0.2.dist-info/RECORD
