Metadata-Version: 2.1
Name: noobai
Version: 0.0.2
Summary: Simple ai tools created by 蓝白bw
Author-email: 蓝白bw <2846131442@qq.com>
License: MIT License
License-File: LICENSE
Requires-Dist: torch
Requires-Dist: numpy
Requires-Dist: tqdm
